easyapp/__init__.py
easyapp/components.py
easyapp/core.py
okton/__init__.py
okton/components.py
okton/core.py
okton-0.1.dist-info/METADATA
okton-0.1.dist-info/WHEEL
okton-0.1.dist-info/top_level.txt
okton-0.1.dist-info/RECORD
