Metadata-Version: 2.4
Name: okton
Version: 0.1
Summary: Une bibliothèque simple pour créer des apps mobiles en Python
Requires-Dist: kivy
Dynamic: requires-dist
Dynamic: summary
